honu/__init__.py
honu/version.py
honudb-0.1.0.dist-info/LICENSE
honudb-0.1.0.dist-info/METADATA
honudb-0.1.0.dist-info/WHEEL
honudb-0.1.0.dist-info/top_level.txt
honudb-0.1.0.dist-info/zip-safe
honudb-0.1.0.dist-info/RECORD
